benchrun/__init__.py
benchrun/_benchmark.py
benchrun/_benchmark_list.py
benchrun/_version.py
benchrun/cache.py
benchrun/case.py
tests/__init__.py
tests/test_benchmark.py
tests/test_benchmark_list.py
tests/test_cache.py
tests/test_case.py
tests/test_version.py
benchrun-2023.2.8.dist-info/LICENSE.txt
benchrun-2023.2.8.dist-info/METADATA
benchrun-2023.2.8.dist-info/WHEEL
benchrun-2023.2.8.dist-info/top_level.txt
benchrun-2023.2.8.dist-info/RECORD
