Metadata-Version: 2.1
Name: benchrun
Version: 2023.2.8
Summary: Tools for Running Benchmarks
Home-page: https://github.com/conbench/conbench/tree/main/benchrun
Maintainer: Voltron Data
Maintainer-email: conbench@voltrondata.com
Classifier: Programming Language :: Python :: 3.8
Classifier: License :: OSI Approved :: Apache Software License
Requires-Python: >=3.8
License-File: LICENSE.txt
Requires-Dist: benchadapt
